<?xml version="1.0" encoding="utf-8"?>

    <item>
        <title>[COLOR white][B]A Dominadora[/B][/COLOR]</title>
        <link>http://repo.maxseries.xyz/american/1/4M3R1C4N.H0RR0R.5T0RY.S03E01.mp4</link>
        <thumbnail>https://goo.gl/nQSzWT<thumbnail>
        <fanart>https://goo.gl/7HFyYt</fanart>
    </item>
    
    <item>
        <title>[COLOR white][B]As Partes do Garoto[/B][/COLOR]</title>
        <link>http://repo.maxseries.xyz/american/1/4M3R1C4N.H0RR0R.5T0RY.S03E02.mp4</link>
        <thumbnail>https://goo.gl/nQSzWT<thumbnail>
        <fanart>https://goo.gl/7HFyYt</fanart>
    </item>
    
    <item>
        <title>[COLOR white][B]As Substituições[/B][/COLOR]</title>
        <link>http://repo.maxseries.xyz/american/1/4M3R1C4N.H0RR0R.5T0RY.S03E03.mp4</link>
        <thumbnail>https://goo.gl/nQSzWT<thumbnail>
        <fanart>https://goo.gl/7HFyYt</fanart>
    </item>
    
    <item>
        <title>[COLOR white][B]Brincadeiras Assustadoras[/B][/COLOR]</title>
        <link>http://repo.maxseries.xyz/american/1/4M3R1C4N.H0RR0R.5T0RY.S03E04.mp4</link>
        <thumbnail>https://goo.gl/nQSzWT<thumbnail>
        <fanart>https://goo.gl/7HFyYt</fanart>
    </item>
    
    <item>
        <title>[COLOR white][B]Queime, Bruxa. Queime![/B][/COLOR]</title>
        <link>http://repo.maxseries.xyz/american/1/4M3R1C4N.H0RR0R.5T0RY.S03E05.mp4</link>
        <thumbnail>https://goo.gl/nQSzWT<thumbnail>
        <fanart>https://goo.gl/7HFyYt</fanart>
    </item>

    <item>
        <title>[COLOR white][B]A Vinda do Homem do Machado[/B][/COLOR]</title>
        <link>http://repo.maxseries.xyz/american/1/4M3R1C4N.H0RR0R.5T0RY.S03E06.mp4</link>
        <thumbnail>https://goo.gl/nQSzWT<thumbnail>
        <fanart>https://goo.gl/7HFyYt</fanart>
    </item>
        
    <item>
        <title>[COLOR white][B]O Morto[/B][/COLOR]</title>
        <link>http://repo.maxseries.xyz/american/1/4M3R1C4N.H0RR0R.5T0RY.S03E07.mp4</link>
        <thumbnail>https://goo.gl/nQSzWT<thumbnail>
        <fanart>https://goo.gl/7HFyYt</fanart>
    </item>
    
    <item>
        <title>[COLOR white][B]O Ritual Sagrado[/B][/COLOR]</title>
        <link>http://repo.maxseries.xyz/american/1/4M3R1C4N.H0RR0R.5T0RY.S03E08.mp4</link>
        <thumbnail>https://goo.gl/nQSzWT<thumbnail>
        <fanart>https://goo.gl/7HFyYt</fanart>
    </item>
            
    <item>
        <title>[COLOR white][B]Cabeça[/B][/COLOR]</title>
        <link>http://repo.maxseries.xyz/american/1/4M3R1C4N.H0RR0R.5T0RY.S03E09.mp4</link>
        <thumbnail>https://goo.gl/nQSzWT<thumbnail>
        <fanart>https://goo.gl/7HFyYt</fanart>
    </item>            
            
    <item>
        <title>[COLOR white][B]Os Prazeres Mágicos de Stevie Nicks[/B][/COLOR]</title>
        <link>http://repo.maxseries.xyz/american/1/4M3R1C4N.H0RR0R.5T0RY.S03E10.mp4</link>
        <thumbnail>https://goo.gl/nQSzWT<thumbnail>
        <fanart>https://goo.gl/7HFyYt</fanart>
    </item>  
            
    <item>
        <title>[COLOR white][B]Protejam o Clã[/B][/COLOR]</title>
        <link>http://repo.maxseries.xyz/american/1/4M3R1C4N.H0RR0R.5T0RY.S03E11.mp4</link>
        <thumbnail>https://goo.gl/nQSzWT<thumbnail>
        <fanart>https://goo.gl/7HFyYt</fanart>
    </item>  
            
    <item>
        <title>[COLOR white][B]Vá Para o Inferno[/B][/COLOR]</title>
        <link>http://repo.maxseries.xyz/american/1/4M3R1C4N.H0RR0R.5T0RY.S03E12.mp4</link>
        <thumbnail>https://goo.gl/nQSzWT<thumbnail>
        <fanart>https://goo.gl/7HFyYt</fanart>
    </item>
            
    <item>
        <title>[COLOR white][B]As Sete Maravilhas[/B][/COLOR]</title>
        <link>http://repo.maxseries.xyz/american/1/4M3R1C4N.H0RR0R.5T0RY.S03E13.mp4</link>
        <thumbnail>https://goo.gl/nQSzWT<thumbnail>
        <fanart>https://goo.gl/7HFyYt</fanart>
    </item>